MANIFEST.in
README.md
setup.cfg
setup.py
darksky_catalog/__init__.py
darksky_catalog/catalog.py
darksky_catalog/dataset.py
darksky_catalog.egg-info/PKG-INFO
darksky_catalog.egg-info/SOURCES.txt
darksky_catalog.egg-info/dependency_links.txt
darksky_catalog.egg-info/requires.txt
darksky_catalog.egg-info/top_level.txt